<?xml version="1.0"?>
<level2> <!-- Canteeen -->

	<!-- Walls -->
	<!-- outter walls -->
	<wall sX="0" sY="0" eX="1200" eY="20"></wall>
	<wall sX="0" sY="580" eX="1200" eY="600"></wall>
	<wall sX="0" sY="0" eX="20" eY="600"></wall>
	<wall sX="1180" sY="0" eX="1200" eY="600"></wall>
	
	<!-- big room -->
	<wall sX="300" sY="140" eX="320" eY="350"></wall>
	<wall sX="300" sY="430" eX="320" eY="600"></wall>
	<wall sX="0" sY="140" eX="300" eY="160"></wall>
	
	<!-- left small room -->
	<wall sX="500" sY="260" eX="750" eY="280"></wall>
	<wall sX="750" sY="220" eX="770" eY="280"></wall>
	<wall sX="750" sY="0" eX="770" eY="140"></wall>
	<wall sX="500" sY="0" eX="520" eY="260"></wall>
	<!-- right small room -->
	<wall sX="950" sY="260" eX="1200" eY="280"></wall>
	<wall sX="950" sY="220" eX="970" eY="280"></wall>
	<wall sX="950" sY="0" eX="970" eY="140"></wall>
	
	
	<!-- Rooms -->
	<room sX="500" sY="280" eX="1180" eY="580"></room>
	<room sX="310" sY="140" eX="500" eY="580"></room>
	<room sX="20" sY="20" eX="500" eY="140"></room>
	<room sX="770" sY="20" eX="960" eY="280"></room>
	<room sX="0" sY="140" eX="310" eY="600"></room>
	<room sX="500" sY="0" eX="770" eY="280"></room>
	<room sX="960" sY="0" eX="1200" eY="280"></room>
	
	
	<!-- Tables -->
	<desk sX="75" sY="250" eX="225" eY="500"></desk>
	
	<desk sX="1000" sY="510" eX="1100" eY="530"></desk>
	<desk sX="1000" sY="410" eX="1100" eY="430"></desk>
	<desk sX="1000" sY="310" eX="1100" eY="330"></desk>
	
	<desk sX="800" sY="510" eX="900" eY="530"></desk>
	<desk sX="800" sY="410" eX="900" eY="430"></desk>
	<desk sX="800" sY="310" eX="900" eY="330"></desk>
	
	<desk sX="600" sY="510" eX="700" eY="530"></desk>
	<desk sX="600" sY="410" eX="700" eY="430"></desk>
	<desk sX="600" sY="310" eX="700" eY="330"></desk>
	
	<desk sX="520" sY="100" eX="540" eY="200"></desk>
	<desk sX="1000" sY="20" eX="1100" eY="40"></desk>
	
	<guard sX="965" sY="400" startingOrientation="u" onCollisionTurn="b"></guard>
	<guard sX="730" sY="400" startingOrientation="d" onCollisionTurn="b"></guard>
	<guard sX="540" sY="400" startingOrientation="u" onCollisionTurn="b"></guard>
	<guard sX="740" sY="360" startingOrientation="l" onCollisionTurn="b"></guard>
	
	<!-- Doors -->
	<door sX="950" sY="140" orientation="v" locktype="f"></door>
	<door sX="300" sY="350" orientation="v" locktype="l" pins="4"></door>
	<door sX="750" sY="140" orientation="v" locktype="l" pins="4"></door>
	
	<!-- Cameras -->
	<camera pointOneX="857" pointOneY="20" pointTwoX="770" pointTwoY="280" pointThreeX="950" pointThreeY="280" cameraPointX="857" cameraPointY="20"></camera>
	<camera pointOneX="320" pointOneY="300" pointTwoX="500" pointTwoY="195" pointThreeX="500" pointThreeY="405" cameraPointX="325" cameraPointY="295" rotate="1"></camera>
	<camera pointOneX="320" pointOneY="480" pointTwoX="500" pointTwoY="375" pointThreeX="500" pointThreeY="580" cameraPointX="325" cameraPointY="475" rotate="1"></camera>
	
	<terminal sX="520" sY="120" connectedCamID="1" codeLength="4" rotate="3"></terminal>
	<terminal sX="1020" sY="410" connectedCamID="0" codeLength="4" rotate="0"></terminal>
	<terminal sX="630" sY="510" connectedCamID="2" codeLength="4" rotate="0"></terminal>
	
	<!-- Servers -->
	<server sX="1100" sY="170" eX="1180" eY="250" level="Levels/Level_1/Server/level.txt" solution="Levels/Level_1//Server/solution.txt"></server>
	<wall sX= "1100" sY="170" eX="1180" eY="250"></wall>

	<!-- End -->
	<end sX="20" sY="40" eX="60" eY="120" rotate="3"></end>
	
	<player sX="1100" sY="520"></player>
	<dataAmount needed = "1"></dataAmount>
	<mug sX="190" sY="250" connectedDoorID="0"></mug>
	<paper sX="1000" sY="510" dataPath="Levels/Level_2/0.txt"></paper>
	<paper sX="600" sY="310" dataPath="Levels/Level_2/1.txt"></paper>
	<paper sX="1030" sY="20" dataPath="Levels/Level_2/2.txt"></paper>
	
	<miscObj sX="460" sY="20" eX="500" eY="60" displayImage="Art_Assets/In_Game/Levels/Misc/plant2.png"></miscObj>
	<miscObj sX="320" sY="540" eX="360" eY="580" displayImage="Art_Assets/In_Game/Levels/Misc/plant.png"></miscObj>
	<miscObj sX="910" sY="20" eX="950" eY="60" displayImage="Art_Assets/In_Game/Levels/Misc/plant2.png"></miscObj>
	<miscObj sX="1140" sY="280" eX="1180" eY="320" displayImage="Art_Assets/In_Game/Levels/Misc/plant.png"></miscObj>
	<miscObj sX="20" sY="160" eX="60" eY="200" displayImage="Art_Assets/In_Game/Levels/Misc/plant2.png"></miscObj>
	<miscObj sX="20" sY="540" eX="60" eY="580" displayImage="Art_Assets/In_Game/Levels/Misc/plant.png"></miscObj>
	
	<miscObj sX="110" sY="160" eX="140" eY="190" displayImage="Art_Assets/In_Game/Levels/Misc/seat00.png"></miscObj>
	<miscObj sX="140" sY="160" eX="170" eY="190" displayImage="Art_Assets/In_Game/Levels/Misc/seat10.png"></miscObj>
	<miscObj sX="170" sY="160" eX="200" eY="190" displayImage="Art_Assets/In_Game/Levels/Misc/seat01.png"></miscObj>

	<miscObj sX="110" sY="550" eX="140" eY="580" displayImage="Art_Assets/In_Game/Levels/Misc/seat22.png"></miscObj>
	<miscObj sX="140" sY="550" eX="170" eY="580" displayImage="Art_Assets/In_Game/Levels/Misc/seat12.png"></miscObj>
	<miscObj sX="170" sY="550" eX="200" eY="580" displayImage="Art_Assets/In_Game/Levels/Misc/seat21.png"></miscObj>
	
	<miscObj sX="600" sY="20" eX="630" eY="50" displayImage="Art_Assets/In_Game/Levels/Misc/seat00.png"></miscObj>
	<miscObj sX="630" sY="20" eX="660" eY="50" displayImage="Art_Assets/In_Game/Levels/Misc/seat01.png"></miscObj>
	
	<miscObj sX="1150" sY="60" eX="1180" eY="90" displayImage="Art_Assets/In_Game/Levels/Misc/seat20.png"></miscObj>
	<miscObj sX="1150" sY="90" eX="1180" eY="110" displayImage="Art_Assets/In_Game/Levels/Misc/seat02.png"></miscObj>
	
	<miscObj sX="570" sY="120" eX="600" eY="150" displayImage="Art_Assets/In_Game/Levels/Misc/chair0.png"></miscObj>
	<miscObj sX="1030" sY="70" eX="1060" eY="100" displayImage="Art_Assets/In_Game/Levels/Misc/chair2.png"></miscObj>
	
</level2>

